invisibleroads_macros_process/__init__.py
invisibleroads_macros_process-0.2.0.dist-info/METADATA
invisibleroads_macros_process-0.2.0.dist-info/WHEEL
invisibleroads_macros_process-0.2.0.dist-info/top_level.txt
invisibleroads_macros_process-0.2.0.dist-info/zip-safe
invisibleroads_macros_process-0.2.0.dist-info/RECORD
