Metadata-Version: 2.1
Name: invisibleroads-macros-process
Version: 0.2.0
Summary: Shortcut functions for process operations
Home-page: https://github.com/invisibleroads/invisibleroads-macros-process
Author: Roy Hyunjin Han
Author-email: rhh@crosscompute.com
Keywords: invisibleroads
Classifier: Programming Language :: Python
Classifier: License :: OSI Approved :: MIT License
Provides-Extra: test
Requires-Dist: pytest ; extra == 'test'
Requires-Dist: pytest-cov ; extra == 'test'
Requires-Dist: pytest-mock ; extra == 'test'
